<Product id="PGxxxxx">
  <Name>Name</Name>
  <Seed Name="" Type="RAPSODY" GroupId="ECD_DISJONCTEUR" ItemId="MG4_13271"/>
  <Content>
    <Characteristics>
      <Characteristic>
        <Name/>
        <Id>PRT_INST</Id>
        <SetValues>
          <Value>
            <Name/>
            <Id></Id>
          </Value>
        </SetValues>
      </Characteristic>
      <Characteristic>
        <Name/>
        <Id>PRT_PERFO</Id>
        <SetValues>
          <Value>
            <Name/>
            <Id>F</Id>
          </Value>
        </SetValues>
      </Characteristic>
      <Characteristic>
        <Name/>
        <Id>PRT_CDECL</Id>
        <SetValues>
          <Value>
            <Name/>
            <Id>CLASS</Id>
          </Value>
        </SetValues>
      </Characteristic>
      <Characteristic>
        <Name/>
        <Id>PRT_CAL</Id>
        <SetValues>
          <Value>
            <Name/>
            <Id>CAL</Id>
          </Value>
        </SetValues>
      </Characteristic>
      <Characteristic>
        <Name/>
        <Id>PRT_NBPPP</Id>
        <SetValues>
          <Value>
            <Name/>
            <Id>PROT</Id>
          </Value>
        </SetValues>
      </Characteristic>
      <Characteristic>
        <Name/>
        <Id>PRT_NORM</Id>
        <SetValues>
          <Value>
            <Name/>
            <Id>NORM</Id>
          </Value>
        </SetValues>
      </Characteristic>
      <Characteristic>
        <Name/>
        <Id>PRT_FREQ</Id>
        <SetValues>
          <Value>
            <Name/>
            <Id>FREQ</Id>
          </Value>
        </SetValues>
      </Characteristic>
      <Characteristic>
        <Name/>
        <Id>PRT_ICC</Id>
        <SetValues>
          <Value>
            <Name/>
            <Id>ICC</Id>
          </Value>
        </SetValues>
      </Characteristic>
      <Characteristic>
        <Name/>
        <Id>PRT_DIFF</Id>
        <SetValues>
          <Value>
            <Name/>
            <Id>DIFF</Id>
          </Value>
        </SetValues>
      </Characteristic>
      <Characteristic>
        <Name/>
        <Id>PRT_VISU</Id>
        <SetValues>
          <Value>
            <Name/>
            <Id>VISU</Id>
          </Value>
        </SetValues>
      </Characteristic>
      <Characteristic>
        <Name/>
        <Id>PRT_TCDE</Id>
        <SetValues>
          <Value>
            <Name/>
            <Id>N</Id>
          </Value>
        </SetValues>
      </Characteristic>
      <Characteristic>
        <Name/>
        <Id>PRT_BDCLS</Id>
        <SetValues>
          <Value>
            <Name/>
            <Id></Id>
          </Value>
        </SetValues>
      </Characteristic>
      <Characteristic>
        <Name/>
        <Id>PRT_BDSEN</Id>
        <SetValues>
          <Value>
            <Name/>
            <Id>0</Id>
          </Value>
        </SetValues>
      </Characteristic>
      <Characteristic>
        <Name/>
        <Id>PRT_REF</Id>
        <SetValues>
          <Value>
            <Name/>
            <Id>REF</Id>
          </Value>
        </SetValues>
      </Characteristic>
    </Characteristics>
  </Content>
</Product>